pdffonts_python/__init__.py
pdffonts_python/pdffonts_python.py
pdffonts_python-0.1.5.dist-info/licenses/LICENSE
pdffonts_python-0.1.5.dist-info/METADATA
pdffonts_python-0.1.5.dist-info/WHEEL
pdffonts_python-0.1.5.dist-info/top_level.txt
pdffonts_python-0.1.5.dist-info/RECORD
