Metadata-Version: 2.4
Name: pdffonts-python
Version: 0.1.5
Summary: A Python wrapper for the pdffonts command.
Author-email: jackson <58273860+neverabsolute@users.noreply.github.com>
License-Expression: MIT
Project-URL: Source, https://github.com/neverabsolute/pdffonts-python
Project-URL: Tracker, https://github.com/neverabsolute/pdffonts-python/issues
Keywords: pdffonts,pdf,wrapper
Classifier: Programming Language :: Python :: 3
Classifier: Operating System :: POSIX :: Linux
Requires-Python: >=3.6
License-File: LICENSE
Dynamic: license-file
